log_ext/__init__.py
log_ext/log_ext.py
log_ext-1.1.0.dist-info/LICENSE
log_ext-1.1.0.dist-info/METADATA
log_ext-1.1.0.dist-info/WHEEL
log_ext-1.1.0.dist-info/top_level.txt
log_ext-1.1.0.dist-info/RECORD
